MANIFEST.in
requirements.txt
setup.cfg
setup.py
spectrometer/__init__.py
spectrometer/server.py
spectrometer/utils.py
spectrometer/views.py
spectrometer.egg-info/PKG-INFO
spectrometer.egg-info/SOURCES.txt
spectrometer.egg-info/dependency_links.txt
spectrometer.egg-info/entry_points.txt
spectrometer.egg-info/requires.txt
spectrometer.egg-info/top_level.txt
spectrometer/api/__init__.py
spectrometer/api/gerrit.py
spectrometer/api/git.py
spectrometer/handlers/__init__.py
spectrometer/handlers/gerrit.py
spectrometer/handlers/git.py