Metadata-Version: 1.1
Name: spectrometer
Version: 0.0.1
Summary: UNKNOWN
Home-page: https://wiki.opendaylight.org/view/Spectrometer
Author: OpenDaylight Spectrometer Project
Author-email: spectrometer-dev@lists.opendaylight.org
License: EPL
Platform: UNKNOWN
Classifier: Development Status :: 1 - Planning
Classifier: Operating System :: POSIX :: Linux
Classifier: Programming Language :: Python
Classifier: Programming Language :: Python :: 3.5
